spider_scrape/__init__.py
spider_scrape/arango_db.py
spider_scrape/bs.py
spider_scrape/db.py
spider_scrape/py.typed
spider_scrape/scraper.py
spider_scrape-0.0.4.dist-info/LICENSE
spider_scrape-0.0.4.dist-info/METADATA
spider_scrape-0.0.4.dist-info/WHEEL
spider_scrape-0.0.4.dist-info/RECORD
